Metadata-Version: 2.1
Name: kabaret.flow_entities
Version: 1.0.0
Summary: A kabaret.flow extension providing searchable large collections of entities.
Home-page: https://gitlab.com/kabaretstudio/kabaret.flow_entities
Author: Damien "dee" Coureau
Author-email: kabaret-dev@googlegroups.com
License: LGPLv3+
Keywords: kabaret pipeline dataflow workflow mongodb
Classifier: Development Status :: 3 - Alpha
Classifier: Intended Audience :: Developers
Classifier: Operating System :: OS Independent
Classifier: Programming Language :: Python :: 2.7
Classifier: Programming Language :: Python :: 3.7
Classifier: License :: OSI Approved :: GNU Lesser General Public License v3 or later (LGPLv3+)
License-File: LICENSE
Requires-Dist: kabaret>=2.1.5
Requires-Dist: pymongo
